clickzetta_dbutils/.DS_Store
clickzetta_dbutils/__init__.py
clickzetta_dbutils/db_utils.py
clickzetta_dbutils/version.py
clickzetta_dbutils/__pycache__/AESCryptor.cpython-310-pytest-8.2.1.pyc
clickzetta_dbutils/__pycache__/__init__.cpython-310.pyc
clickzetta_dbutils/__pycache__/db_utils.cpython-310.pyc
clickzetta_dbutils/__pycache__/version.cpython-310.pyc
pyarmor_runtime_000000/__init__.py
pyarmor_runtime_000000/__pycache__/__init__.cpython-310.pyc
pyarmor_runtime_000000/alpine_x86_64/pyarmor_runtime.so
pyarmor_runtime_000000/darwin_universal/pyarmor_runtime.so
pyarmor_runtime_000000/linux_x86_64/pyarmor_runtime.so
clickzetta_dbutils-1.0.26.dist-info/METADATA
clickzetta_dbutils-1.0.26.dist-info/WHEEL
clickzetta_dbutils-1.0.26.dist-info/top_level.txt
clickzetta_dbutils-1.0.26.dist-info/RECORD
