Metadata-Version: 2.4
Name: clickzetta-dbutils
Version: 1.0.26
Summary: clickzetta dbutils
Author-email: "lin.zhang" <lin.zhang@clickzetta.com>
Project-URL: documentation, https://www.yunqi.tech/
Platform: Posix
Platform: MacOS X
Classifier: Development Status :: 3 - Alpha
Requires-Python: >=3.10
Requires-Dist: sqlalchemy>=1.4.0
Requires-Dist: numpy==1.24.4
Requires-Dist: psycopg2-binary
Requires-Dist: mysql-connector-python
Requires-Dist: crypto
Requires-Dist: pycryptodome
Provides-Extra: dev
Requires-Dist: pytest==8.2.1; extra == "dev"
Requires-Dist: build; extra == "dev"
Requires-Dist: pytest-xdist; extra == "dev"
Requires-Dist: pyarmor; extra == "dev"
Requires-Dist: pyarmor.cli.core.darwin; extra == "dev"
Requires-Dist: pyarmor.cli.core.linux; extra == "dev"
Requires-Dist: pyarmor.cli.core.alpine; extra == "dev"
Provides-Extra: cliclzetta-legecy-sdk
Requires-Dist: clickzetta-connector; extra == "cliclzetta-legecy-sdk"
Requires-Dist: clickzetta-sqlalchemy; extra == "cliclzetta-legecy-sdk"
Provides-Extra: cliclzetta
Requires-Dist: clickzetta-connector-python; extra == "cliclzetta"
